pyDataverse/__init__.py
pyDataverse/api.py
pyDataverse/auth.py
pyDataverse/docs/source/_images/collection_dataset.png
pyDataverse/docs/source/_static/.gitkeep
pyDataverse/docs/source/_templates/layout.html
pyDataverse/docs/source/_templates/sidebar_intro.html
pyDataverse/docs/source/_templates/sidebar_related-links.html
pyDataverse/docs/source/community/contact.rst
pyDataverse/docs/source/community/releases.rst
pyDataverse/docs/source/conf.py
pyDataverse/docs/source/contributing/contributing.rst
pyDataverse/docs/source/index.rst
pyDataverse/docs/source/reference.rst
pyDataverse/docs/source/snippets/pip-install.rst
pyDataverse/docs/source/snippets/requirements.rst
pyDataverse/docs/source/snippets/warning_production.rst
pyDataverse/docs/source/user/advanced-usage.rst
pyDataverse/docs/source/user/basic-usage.rst
pyDataverse/docs/source/user/csv-templates.rst
pyDataverse/docs/source/user/faq.rst
pyDataverse/docs/source/user/installation.rst
pyDataverse/docs/source/user/resources.rst
pyDataverse/docs/source/user/use-cases.rst
pyDataverse/exceptions.py
pyDataverse/models.py
pyDataverse/schemas/json/datafile_upload_schema.json
pyDataverse/schemas/json/dataset_upload_default_schema.json
pyDataverse/schemas/json/dataverse_upload_schema.json
pyDataverse/schemas/json/dspace_schema.json
pyDataverse/templates/datafiles.csv
pyDataverse/templates/datasets.csv
pyDataverse/templates/dataverses.csv
pyDataverse/utils.py
pydataverse-0.3.5.dist-info/LICENSE.txt
pydataverse-0.3.5.dist-info/METADATA
pydataverse-0.3.5.dist-info/WHEEL
pydataverse-0.3.5.dist-info/RECORD
