Metadata-Version: 2.3
Name: pyDataverse
Version: 0.3.5
Summary: A Python module for Dataverse.
License: MIT
Author: Stefan Kasberger
Author-email: stefan.kasberger@univie.ac.at
Requires-Python: >=3.8.1,<4.0.0
Classifier: License :: OSI Approved :: MIT License
Classifier: Programming Language :: Python :: 3
Classifier: Programming Language :: Python :: 3.9
Classifier: Programming Language :: Python :: 3.10
Classifier: Programming Language :: Python :: 3.11
Classifier: Programming Language :: Python :: 3.12
Classifier: Programming Language :: Python :: 3.13
Requires-Dist: httpx (>=0.27,<0.30)
Requires-Dist: jsonschema (>=4.21.1,<5.0.0)
Project-URL: Repository, https://github.com/gdcc/pyDataverse
